denton/__init__.py
denton-0.0.2.dist-info/METADATA
denton-0.0.2.dist-info/WHEEL
denton-0.0.2.dist-info/top_level.txt
denton-0.0.2.dist-info/RECORD
