Metadata-Version: 2.1
Name: denton
Version: 0.0.2
Summary: function to interpolate data using the denton procedure.
Home-page: https://github.com/MaxLugo/denton
Author: Max Lugo D
Author-email: maxlugo20@gmail.com
License: UNKNOWN
Platform: UNKNOWN
Classifier: Programming Language :: Python :: 3
Classifier: License :: OSI Approved :: MIT License
Classifier: Operating System :: OS Independent
Requires-Python: >=3.0
